passwordUtils/__init__.py
passwordUtils-0.0.1.dist-info/METADATA
passwordUtils-0.0.1.dist-info/WHEEL
passwordUtils-0.0.1.dist-info/top_level.txt
passwordUtils-0.0.1.dist-info/RECORD
