Metadata-Version: 2.1
Name: passwordUtils
Version: 0.0.1
Summary: Utilities for Password Management
Home-page: UNKNOWN
Author: Olliejohnson
Author-email: oliver.joseph.johnson@gmail.com
License: UNKNOWN
Keywords: python,first package
Platform: UNKNOWN
Classifier: Development Status :: 3 - Alpha
Classifier: Intended Audience :: Education
Classifier: Programming Language :: Python :: 2
Classifier: Programming Language :: Python :: 3
Classifier: Operating System :: MacOS :: MacOS X
Classifier: Operating System :: Microsoft :: Windows
